tui_adf/Funktionen.py
tui_adf/__init__.py
tui_adf-0.10.dist-info/LICENSE
tui_adf-0.10.dist-info/METADATA
tui_adf-0.10.dist-info/WHEEL
tui_adf-0.10.dist-info/top_level.txt
tui_adf-0.10.dist-info/RECORD
