Metadata-Version: 2.1
Name: tui-adf
Version: 0.10
Summary: Funktionen für Lehrveranstaltung Analoge Digitale Filter
Home-page: UNKNOWN
Author: Michael Riesmeyer
Author-email: Michael.Riesmeyer@tu-ilmenau.de
License: UNKNOWN
Platform: UNKNOWN
Classifier: Programming Language :: Python :: 3
Classifier: License :: OSI Approved :: MIT License
Classifier: Operating System :: OS Independent
Requires-Dist: numpy
Requires-Dist: scipy
Requires-Dist: PyDynamic
